geoquery/__init__.py
geoquery/bin.py
geoquery/parse.py
geoquery/remote.py
geoquery-1.0.1.dist-info/METADATA
geoquery-1.0.1.dist-info/WHEEL
geoquery-1.0.1.dist-info/entry_points.txt
geoquery-1.0.1.dist-info/top_level.txt
geoquery-1.0.1.dist-info/RECORD
